<annotation>
  <folder>images</folder>
  <filename>00aa707.jpg</filename>
  <segmented>0</segmented>
  <size>
    <width>1920</width>
    <height>1080</height>
    <depth>3</depth>
  </size>
  <object>
    <name>regulamentacao</name>
    <pose>Unspecified</pose>
    <truncated>0</truncated>
    <difficult>0</difficult>
    <bndbox>
      <xmin>484</xmin>
      <ymin>482</ymin>
      <xmax>546</xmax>
      <ymax>532</ymax>
    </bndbox>
  </object>
  <object>
    <name>regulamentacao</name>
    <pose>Unspecified</pose>
    <truncated>0</truncated>
    <difficult>0</difficult>
    <bndbox>
      <xmin>491</xmin>
      <ymin>527</ymin>
      <xmax>541</xmax>
      <ymax>578</ymax>
    </bndbox>
  </object>
  <object>
    <name>advertencia</name>
    <pose>Unspecified</pose>
    <truncated>0</truncated>
    <difficult>0</difficult>
    <bndbox>
      <xmin>572</xmin>
      <ymin>481</ymin>
      <xmax>643</xmax>
      <ymax>546</ymax>
    </bndbox>
  </object>
</annotation>
