<annotation>
  <folder>images</folder>
  <filename>00aa564_rotate[7].png</filename>
  <segmented>0</segmented>
  <size>
    <width>1802</width>
    <height>853</height>
    <depth>3</depth>
  </size>
  <object>
    <name>advertencia</name>
    <pose>Unspecified</pose>
    <truncated>0</truncated>
    <difficult>0</difficult>
    <bndbox>
      <xmin>1222</xmin>
      <ymin>331</ymin>
      <xmax>1277</xmax>
      <ymax>378</ymax>
    </bndbox>
  </object>
  <object>
    <name>regulamentacao</name>
    <pose>Unspecified</pose>
    <truncated>0</truncated>
    <difficult>0</difficult>
    <bndbox>
      <xmin>1233</xmin>
      <ymin>386</ymin>
      <xmax>1281</xmax>
      <ymax>429</ymax>
    </bndbox>
  </object>
</annotation>
