<annotation>
  <folder>images</folder>
  <filename>gp5569.jpg</filename>
  <segmented>0</segmented>
  <size>
    <width>1920</width>
    <height>1080</height>
    <depth>3</depth>
  </size>
  <object>
    <name>regulamentacao</name>
    <pose>Unspecified</pose>
    <truncated>0</truncated>
    <difficult>0</difficult>
    <bndbox>
      <xmin>1013</xmin>
      <ymin>13</ymin>
      <xmax>1080</xmax>
      <ymax>81</ymax>
    </bndbox>
  </object>
  <object>
    <name>regulamentacao</name>
    <pose>Unspecified</pose>
    <truncated>0</truncated>
    <difficult>0</difficult>
    <bndbox>
      <xmin>1341</xmin>
      <ymin>379</ymin>
      <xmax>1405</xmax>
      <ymax>439</ymax>
    </bndbox>
  </object>
</annotation>
