<annotation>
  <folder>images</folder>
  <filename>067 _FlipV _rotate[15].png</filename>
  <segmented/>
  <size>
    <width>1033</width>
    <height>713</height>
    <depth>3</depth>
  </size>
  <object>
    <name>regulamentacao</name>
    <pose>Unspecified</pose>
    <truncated>0</truncated>
    <difficult>0</difficult>
    <bndbox>
      <xmin>831</xmin>
      <ymin>75</ymin>
      <xmax>894</xmax>
      <ymax>121</ymax>
    </bndbox>
  </object>
  <object>
    <name>regulamentacao</name>
    <pose>Unspecified</pose>
    <truncated>0</truncated>
    <difficult>0</difficult>
    <bndbox>
      <xmin>846</xmin>
      <ymin>118</ymin>
      <xmax>905</xmax>
      <ymax>171</ymax>
    </bndbox>
  </object>
</annotation>
