<annotation>
  <folder>images</folder>
  <filename>272 _FlipV _rotate[15].png</filename>
  <segmented/>
  <size>
    <width>1157</width>
    <height>757</height>
    <depth>3</depth>
  </size>
  <object>
    <name>regulamentacao</name>
    <pose>Unspecified</pose>
    <truncated>0</truncated>
    <difficult>0</difficult>
    <bndbox>
      <xmin>799</xmin>
      <ymin>225</ymin>
      <xmax>888</xmax>
      <ymax>296</ymax>
    </bndbox>
  </object>
  <object>
    <name>marcador_de_perigo</name>
    <pose>Unspecified</pose>
    <truncated>0</truncated>
    <difficult>0</difficult>
    <bndbox>
      <xmin>832</xmin>
      <ymin>298</ymin>
      <xmax>878</xmax>
      <ymax>359</ymax>
    </bndbox>
  </object>
</annotation>
