<annotation>
  <folder>images</folder>
  <filename>01ab107.jpg</filename>
  <segmented>0</segmented>
  <size>
    <width>1920</width>
    <height>1080</height>
    <depth>3</depth>
  </size>
  <object>
    <name>regulamentacao</name>
    <pose>Unspecified</pose>
    <truncated>0</truncated>
    <difficult>0</difficult>
    <bndbox>
      <xmin>1403</xmin>
      <ymin>425</ymin>
      <xmax>1475</xmax>
      <ymax>490</ymax>
    </bndbox>
  </object>
  <object>
    <name>regulamentacao</name>
    <pose>Unspecified</pose>
    <truncated>0</truncated>
    <difficult>0</difficult>
    <bndbox>
      <xmin>1411</xmin>
      <ymin>489</ymin>
      <xmax>1476</xmax>
      <ymax>547</ymax>
    </bndbox>
  </object>
</annotation>
